venvipy/__init__.py
venvipy/creator.py
venvipy/dialogs.py
venvipy/get_data.py
venvipy/manage_pip.py
venvipy/pkg_installer.py
venvipy/pkg_manager.py
venvipy/tables.py
venvipy/venvi.py
venvipy/venvipy_rc.py
venvipy/wizard.py
venvipy/platforms/__init__.py
venvipy/platforms/base.py
venvipy/platforms/linux.py
venvipy/platforms/windows.py
venvipy-0.3.9.dist-info/licenses/LICENSE
venvipy-0.3.9.dist-info/METADATA
venvipy-0.3.9.dist-info/WHEEL
venvipy-0.3.9.dist-info/entry_points.txt
venvipy-0.3.9.dist-info/top_level.txt
venvipy-0.3.9.dist-info/RECORD
