Metadata-Version: 2.4
Name: venvipy
Version: 0.3.9
Summary: A GUI for managing Python virtual environments.
Home-page: https://github.com/sinusphi/venvipy
Download-URL: https://github.com/sinusphi/venvipy/archive/v0.3.9.tar.gz
Author: Youssef Serestou
Author-email: sinusphi <sinusphi.sq@gmail.com>
License-Expression: GPL-3.0-or-later
Keywords: python,python3,venv,virtualenvironment,virtual-environment,pyqt,pyqt5,pyqt5-desktop-application,gui
Classifier: Development Status :: 4 - Beta
Classifier: Environment :: X11 Applications
Classifier: Intended Audience :: Developers
Classifier: Intended Audience :: End Users/Desktop
Classifier: Intended Audience :: Other Audience
Classifier: Topic :: Software Development :: Build Tools
Classifier: Topic :: Software Development :: User Interfaces
Classifier: Programming Language :: Python
Classifier: Programming Language :: Python :: 3
Classifier: Programming Language :: Python :: 3.3
Classifier: Programming Language :: Python :: 3.4
Classifier: Programming Language :: Python :: 3.5
Classifier: Programming Language :: Python :: 3.6
Classifier: Programming Language :: Python :: 3.7
Classifier: Programming Language :: Python :: 3.8
Classifier: Programming Language :: Python :: 3.9
Classifier: Programming Language :: Python :: 3.10
Classifier: Programming Language :: Python :: 3.11
Classifier: Programming Language :: Python :: 3.12
Classifier: Programming Language :: Python :: 3.13
Classifier: Programming Language :: Python :: 3.14
Classifier: Programming Language :: Python :: Implementation :: CPython
Requires-Python: >=3.7
License-File: LICENSE
Requires-Dist: PyQt5==5.15.9
Requires-Dist: requests
Requires-Dist: beautifulsoup4
Dynamic: author
Dynamic: download-url
Dynamic: home-page
Dynamic: license-file
Dynamic: requires-python
